encryptly/__init__.py
encryptly/cli.py
encryptly/config.py
encryptly/decorators.py
encryptly/exceptions.py
encryptly/integrations.py
encryptly/vault.py
encryptly-0.1.2.dist-info/licenses/LICENSE
tests/__init__.py
tests/test_rotation.py
encryptly-0.1.2.dist-info/METADATA
encryptly-0.1.2.dist-info/WHEEL
encryptly-0.1.2.dist-info/entry_points.txt
encryptly-0.1.2.dist-info/top_level.txt
encryptly-0.1.2.dist-info/RECORD
